<?xml version="1.0" encoding="utf-8" ?>
<c2layout>
    <name>Layout 1</name>
    <sid>9674559039423459</sid>
    <event-sheet>Event sheet 1</event-sheet>
    <size>
        <width>1708</width>
        <height>960</height>
    </size>
    <margins>
        <horizontal>500</horizontal>
        <vertical>500</vertical>
    </margins>
    <unbounded-scrolling>0</unbounded-scrolling>
    <layers>
        <layer name="Background" sid="3655047421194204">
            <initially-visible>1</initially-visible>
            <background-color>255,255,255</background-color>
            <transparent>0</transparent>
            <parallax>
                <x>1</x>
                <y>1</y>
            </parallax>
            <zoom-rate>1</zoom-rate>
            <opacity>1</opacity>
            <force-own-texture>0</force-own-texture>
            <global>0</global>
            <use-render-cells>0</use-render-cells>
            <blend-mode>0</blend-mode>
            <effect-fallback>0</effect-fallback>
            <instances>
                <instance type="TiledBackground" uid="1">
                    <properties>
                        <initial-visibility>Visible</initial-visibility>
                        <hotspot>Top-left</hotspot>
                    </properties>
                    <blend-mode>0</blend-mode>
                    <effect-fallback>0</effect-fallback>
                    <world>
                        <x>0</x>
                        <y>0</y>
                        <z>0</z>
                        <width>1711</width>
                        <height>959</height>
                        <depth>0</depth>
                        <hotspotX>0</hotspotX>
                        <hotspotY>0</hotspotY>
                        <angle>0</angle>
                        <opacity>1</opacity>
                    </world>
                </instance>
            </instances>
            <effects />
        </layer>
        <layer name="Main" sid="5447813123167266">
            <initially-visible>1</initially-visible>
            <background-color>255,255,255</background-color>
            <transparent>1</transparent>
            <parallax>
                <x>1</x>
                <y>1</y>
            </parallax>
            <zoom-rate>1</zoom-rate>
            <opacity>1</opacity>
            <force-own-texture>0</force-own-texture>
            <global>0</global>
            <use-render-cells>0</use-render-cells>
            <blend-mode>0</blend-mode>
            <effect-fallback>0</effect-fallback>
            <instances>
                <instance type="bullet" uid="3">
                    <properties>
                        <initial-visibility>Visible</initial-visibility>
                        <initial-animation>Default</initial-animation>
                        <initial-frame>0</initial-frame>
                        <collisions>Enabled</collisions>
                    </properties>
                    <behavior-instances>
                        <behavior-instance type="DestroyOutsideLayout" />
                        <behavior-instance type="Bullet">
                            <properties>
                                <speed>400</speed>
                                <acceleration>0</acceleration>
                                <gravity>0</gravity>
                                <bounce-off-solids>No</bounce-off-solids>
                                <set-angle>Yes</set-angle>
                                <initial-state>Enabled</initial-state>
                            </properties>
                        </behavior-instance>
                    </behavior-instances>
                    <blend-mode>0</blend-mode>
                    <effect-fallback>0</effect-fallback>
                    <world>
                        <x>1801</x>
                        <y>305</y>
                        <z>0</z>
                        <width>25</width>
                        <height>16</height>
                        <depth>0</depth>
                        <hotspotX>0.519999981</hotspotX>
                        <hotspotY>0.5</hotspotY>
                        <angle>0</angle>
                        <opacity>1</opacity>
                    </world>
                </instance>
                <instance type="monster" uid="4">
                    <properties>
                        <initial-visibility>Visible</initial-visibility>
                        <initial-animation>Default</initial-animation>
                        <initial-frame>0</initial-frame>
                        <collisions>Enabled</collisions>
                    </properties>
                    <instance-variables>
                        <Health>5</Health>
                    </instance-variables>
                    <behavior-instances>
                        <behavior-instance type="Bullet">
                            <properties>
                                <speed>80</speed>
                                <acceleration>0</acceleration>
                                <gravity>0</gravity>
                                <bounce-off-solids>No</bounce-off-solids>
                                <set-angle>Yes</set-angle>
                                <initial-state>Enabled</initial-state>
                            </properties>
                        </behavior-instance>
                    </behavior-instances>
                    <blend-mode>0</blend-mode>
                    <effect-fallback>0</effect-fallback>
                    <world>
                        <x>218</x>
                        <y>240</y>
                        <z>0</z>
                        <width>145</width>
                        <height>100</height>
                        <depth>0</depth>
                        <hotspotX>0.503448248</hotspotX>
                        <hotspotY>0.5</hotspotY>
                        <angle>0.628143489</angle>
                        <opacity>1</opacity>
                    </world>
                </instance>
                <instance type="explode" uid="5">
                    <properties>
                        <initial-visibility>Visible</initial-visibility>
                        <initial-animation>Default</initial-animation>
                        <initial-frame>0</initial-frame>
                        <collisions>Enabled</collisions>
                    </properties>
                    <behavior-instances>
                        <behavior-instance type="Fade">
                            <properties>
                                <active-at-start>Yes</active-at-start>
                                <fade-in-time>0</fade-in-time>
                                <wait-time>0</wait-time>
                                <fade-out-time>1</fade-out-time>
                                <destroy>After fade out</destroy>
                            </properties>
                        </behavior-instance>
                    </behavior-instances>
                    <blend-mode>1</blend-mode>
                    <effect-fallback>0</effect-fallback>
                    <world>
                        <x>1799</x>
                        <y>219</y>
                        <z>0</z>
                        <width>118</width>
                        <height>101</height>
                        <depth>0</depth>
                        <hotspotX>0.5</hotspotX>
                        <hotspotY>0.504950523</hotspotY>
                        <angle>0</angle>
                        <opacity>1</opacity>
                    </world>
                </instance>
                <instance type="player" uid="6">
                    <properties>
                        <initial-visibility>Visible</initial-visibility>
                        <initial-animation>Default</initial-animation>
                        <initial-frame>0</initial-frame>
                        <collisions>Enabled</collisions>
                    </properties>
                    <behavior-instances>
                        <behavior-instance type="8Direction">
                            <properties>
                                <max-speed>200</max-speed>
                                <acceleration>600</acceleration>
                                <deceleration>500</deceleration>
                                <directions>8 directions</directions>
                                <set-angle>360 degree (smooth)</set-angle>
                                <default-controls>Yes</default-controls>
                                <initial-state>Enabled</initial-state>
                            </properties>
                        </behavior-instance>
                        <behavior-instance type="BoundToLayout">
                            <properties>
                                <bound-by>Edge</bound-by>
                            </properties>
                        </behavior-instance>
                        <behavior-instance type="ScrollTo">
                            <properties>
                                <initial-state>Enabled</initial-state>
                            </properties>
                        </behavior-instance>
                    </behavior-instances>
                    <blend-mode>0</blend-mode>
                    <effect-fallback>0</effect-fallback>
                    <world>
                        <x>848</x>
                        <y>460</y>
                        <z>0</z>
                        <width>108</width>
                        <height>103</height>
                        <depth>0</depth>
                        <hotspotX>0.5</hotspotX>
                        <hotspotY>0.504854381</hotspotY>
                        <angle>0</angle>
                        <opacity>1</opacity>
                    </world>
                </instance>
                <instance type="monster" uid="7">
                    <properties>
                        <initial-visibility>Visible</initial-visibility>
                        <initial-animation>Default</initial-animation>
                        <initial-frame>0</initial-frame>
                        <collisions>Enabled</collisions>
                    </properties>
                    <instance-variables>
                        <Health>5</Health>
                    </instance-variables>
                    <behavior-instances>
                        <behavior-instance type="Bullet">
                            <properties>
                                <speed>80</speed>
                                <acceleration>0</acceleration>
                                <gravity>0</gravity>
                                <bounce-off-solids>No</bounce-off-solids>
                                <set-angle>Yes</set-angle>
                                <initial-state>Enabled</initial-state>
                            </properties>
                        </behavior-instance>
                    </behavior-instances>
                    <blend-mode>0</blend-mode>
                    <effect-fallback>0</effect-fallback>
                    <world>
                        <x>205</x>
                        <y>706</y>
                        <z>0</z>
                        <width>145</width>
                        <height>100</height>
                        <depth>0</depth>
                        <hotspotX>0.503448248</hotspotX>
                        <hotspotY>0.5</hotspotY>
                        <angle>0</angle>
                        <opacity>1</opacity>
                    </world>
                </instance>
                <instance type="monster" uid="8">
                    <properties>
                        <initial-visibility>Visible</initial-visibility>
                        <initial-animation>Default</initial-animation>
                        <initial-frame>0</initial-frame>
                        <collisions>Enabled</collisions>
                    </properties>
                    <instance-variables>
                        <Health>5</Health>
                    </instance-variables>
                    <behavior-instances>
                        <behavior-instance type="Bullet">
                            <properties>
                                <speed>80</speed>
                                <acceleration>0</acceleration>
                                <gravity>0</gravity>
                                <bounce-off-solids>No</bounce-off-solids>
                                <set-angle>Yes</set-angle>
                                <initial-state>Enabled</initial-state>
                            </properties>
                        </behavior-instance>
                    </behavior-instances>
                    <blend-mode>0</blend-mode>
                    <effect-fallback>0</effect-fallback>
                    <world>
                        <x>701</x>
                        <y>162</y>
                        <z>0</z>
                        <width>145</width>
                        <height>100</height>
                        <depth>0</depth>
                        <hotspotX>0.503448248</hotspotX>
                        <hotspotY>0.5</hotspotY>
                        <angle>-3.033429384</angle>
                        <opacity>1</opacity>
                    </world>
                </instance>
                <instance type="monster" uid="9">
                    <properties>
                        <initial-visibility>Visible</initial-visibility>
                        <initial-animation>Default</initial-animation>
                        <initial-frame>0</initial-frame>
                        <collisions>Enabled</collisions>
                    </properties>
                    <instance-variables>
                        <Health>5</Health>
                    </instance-variables>
                    <behavior-instances>
                        <behavior-instance type="Bullet">
                            <properties>
                                <speed>80</speed>
                                <acceleration>0</acceleration>
                                <gravity>0</gravity>
                                <bounce-off-solids>No</bounce-off-solids>
                                <set-angle>Yes</set-angle>
                                <initial-state>Enabled</initial-state>
                            </properties>
                        </behavior-instance>
                    </behavior-instances>
                    <blend-mode>0</blend-mode>
                    <effect-fallback>0</effect-fallback>
                    <world>
                        <x>1313</x>
                        <y>192</y>
                        <z>0</z>
                        <width>145</width>
                        <height>100</height>
                        <depth>0</depth>
                        <hotspotX>0.503448248</hotspotX>
                        <hotspotY>0.5</hotspotY>
                        <angle>-3.043610573</angle>
                        <opacity>1</opacity>
                    </world>
                </instance>
                <instance type="monster" uid="10">
                    <properties>
                        <initial-visibility>Visible</initial-visibility>
                        <initial-animation>Default</initial-animation>
                        <initial-frame>0</initial-frame>
                        <collisions>Enabled</collisions>
                    </properties>
                    <instance-variables>
                        <Health>5</Health>
                    </instance-variables>
                    <behavior-instances>
                        <behavior-instance type="Bullet">
                            <properties>
                                <speed>80</speed>
                                <acceleration>0</acceleration>
                                <gravity>0</gravity>
                                <bounce-off-solids>No</bounce-off-solids>
                                <set-angle>Yes</set-angle>
                                <initial-state>Enabled</initial-state>
                            </properties>
                        </behavior-instance>
                    </behavior-instances>
                    <blend-mode>0</blend-mode>
                    <effect-fallback>0</effect-fallback>
                    <world>
                        <x>1591</x>
                        <y>325</y>
                        <z>0</z>
                        <width>145</width>
                        <height>100</height>
                        <depth>0</depth>
                        <hotspotX>0.503448248</hotspotX>
                        <hotspotY>0.5</hotspotY>
                        <angle>-2.836885452</angle>
                        <opacity>1</opacity>
                    </world>
                </instance>
                <instance type="monster" uid="11">
                    <properties>
                        <initial-visibility>Visible</initial-visibility>
                        <initial-animation>Default</initial-animation>
                        <initial-frame>0</initial-frame>
                        <collisions>Enabled</collisions>
                    </properties>
                    <instance-variables>
                        <Health>5</Health>
                    </instance-variables>
                    <behavior-instances>
                        <behavior-instance type="Bullet">
                            <properties>
                                <speed>80</speed>
                                <acceleration>0</acceleration>
                                <gravity>0</gravity>
                                <bounce-off-solids>No</bounce-off-solids>
                                <set-angle>Yes</set-angle>
                                <initial-state>Enabled</initial-state>
                            </properties>
                        </behavior-instance>
                    </behavior-instances>
                    <blend-mode>0</blend-mode>
                    <effect-fallback>0</effect-fallback>
                    <world>
                        <x>1540</x>
                        <y>590</y>
                        <z>0</z>
                        <width>145</width>
                        <height>100</height>
                        <depth>0</depth>
                        <hotspotX>0.503448248</hotspotX>
                        <hotspotY>0.5</hotspotY>
                        <angle>-2.884916544</angle>
                        <opacity>1</opacity>
                    </world>
                </instance>
                <instance type="monster" uid="12">
                    <properties>
                        <initial-visibility>Visible</initial-visibility>
                        <initial-animation>Default</initial-animation>
                        <initial-frame>0</initial-frame>
                        <collisions>Enabled</collisions>
                    </properties>
                    <instance-variables>
                        <Health>5</Health>
                    </instance-variables>
                    <behavior-instances>
                        <behavior-instance type="Bullet">
                            <properties>
                                <speed>80</speed>
                                <acceleration>0</acceleration>
                                <gravity>0</gravity>
                                <bounce-off-solids>No</bounce-off-solids>
                                <set-angle>Yes</set-angle>
                                <initial-state>Enabled</initial-state>
                            </properties>
                        </behavior-instance>
                    </behavior-instances>
                    <blend-mode>0</blend-mode>
                    <effect-fallback>0</effect-fallback>
                    <world>
                        <x>1150</x>
                        <y>765</y>
                        <z>0</z>
                        <width>145</width>
                        <height>100</height>
                        <depth>0</depth>
                        <hotspotX>0.503448248</hotspotX>
                        <hotspotY>0.5</hotspotY>
                        <angle>-0.811384141</angle>
                        <opacity>1</opacity>
                    </world>
                </instance>
                <instance type="monster" uid="13">
                    <properties>
                        <initial-visibility>Visible</initial-visibility>
                        <initial-animation>Default</initial-animation>
                        <initial-frame>0</initial-frame>
                        <collisions>Enabled</collisions>
                    </properties>
                    <instance-variables>
                        <Health>5</Health>
                    </instance-variables>
                    <behavior-instances>
                        <behavior-instance type="Bullet">
                            <properties>
                                <speed>80</speed>
                                <acceleration>0</acceleration>
                                <gravity>0</gravity>
                                <bounce-off-solids>No</bounce-off-solids>
                                <set-angle>Yes</set-angle>
                                <initial-state>Enabled</initial-state>
                            </properties>
                        </behavior-instance>
                    </behavior-instances>
                    <blend-mode>0</blend-mode>
                    <effect-fallback>0</effect-fallback>
                    <world>
                        <x>624</x>
                        <y>774</y>
                        <z>0</z>
                        <width>145</width>
                        <height>100</height>
                        <depth>0</depth>
                        <hotspotX>0.503448248</hotspotX>
                        <hotspotY>0.5</hotspotY>
                        <angle>-2.87466073</angle>
                        <opacity>1</opacity>
                    </world>
                </instance>
            </instances>
            <effects />
        </layer>
        <layer name="HUD" sid="9834151173583182">
            <initially-visible>1</initially-visible>
            <background-color>255,255,255</background-color>
            <transparent>1</transparent>
            <parallax>
                <x>0</x>
                <y>0</y>
            </parallax>
            <zoom-rate>1</zoom-rate>
            <opacity>1</opacity>
            <force-own-texture>0</force-own-texture>
            <global>0</global>
            <use-render-cells>0</use-render-cells>
            <blend-mode>0</blend-mode>
            <effect-fallback>0</effect-fallback>
            <instances>
                <instance type="Score" uid="14">
                    <properties>
                        <text>Text</text>
                        <initial-visibility>Visible</initial-visibility>
                        <font>Arial,-27,700,0</font>
                        <color>255,255,51</color>
                        <horizontal-alignment>Left</horizontal-alignment>
                        <vertical-alignment>Top</vertical-alignment>
                        <hotspot>Top-left</hotspot>
                        <wrapping>Word</wrapping>
                        <line-height>0</line-height>
                    </properties>
                    <blend-mode>0</blend-mode>
                    <effect-fallback>0</effect-fallback>
                    <world>
                        <x>4</x>
                        <y>2.818649292</y>
                        <z>0</z>
                        <width>365</width>
                        <height>54</height>
                        <depth>0</depth>
                        <hotspotX>0</hotspotX>
                        <hotspotY>0</hotspotY>
                        <angle>0</angle>
                        <opacity>1</opacity>
                    </world>
                </instance>
                <instance type="GameOver" uid="15">
                    <properties>
                        <text>Game Over</text>
                        <initial-visibility>Invisible</initial-visibility>
                        <font>Arial Black,-33,900,0</font>
                        <color>255,0,0</color>
                        <horizontal-alignment>Center</horizontal-alignment>
                        <vertical-alignment>Center</vertical-alignment>
                        <hotspot>Center</hotspot>
                        <wrapping>Word</wrapping>
                        <line-height>0</line-height>
                    </properties>
                    <blend-mode>0</blend-mode>
                    <effect-fallback>0</effect-fallback>
                    <world>
                        <x>412</x>
                        <y>140</y>
                        <z>0</z>
                        <width>200</width>
                        <height>111</height>
                        <depth>0</depth>
                        <hotspotX>0.5</hotspotX>
                        <hotspotY>0.5</hotspotY>
                        <angle>0</angle>
                        <opacity>1</opacity>
                    </world>
                </instance>
                <instance type="PlayAgainButton" uid="16">
                    <properties>
                        <type>Button</type>
                        <text>Play Again</text>
                        <tooltip></tooltip>
                        <initial-visibility>Invisible</initial-visibility>
                        <enabled>Yes</enabled>
                        <auto-font-size>Yes</auto-font-size>
                        <id-optional></id-optional>
                        <checked>No</checked>
                    </properties>
                    <blend-mode>0</blend-mode>
                    <effect-fallback>0</effect-fallback>
                    <world>
                        <x>369</x>
                        <y>247</y>
                        <z>0</z>
                        <width>72</width>
                        <height>24</height>
                        <depth>0</depth>
                        <hotspotX>0</hotspotX>
                        <hotspotY>0</hotspotY>
                    </world>
                </instance>
                <instance type="HighScore" uid="17">
                    <properties>
                        <text>New High Score!</text>
                        <initial-visibility>Invisible</initial-visibility>
                        <font>Arial,-23,700,0</font>
                        <color>255,255,51</color>
                        <horizontal-alignment>Left</horizontal-alignment>
                        <vertical-alignment>Top</vertical-alignment>
                        <hotspot>Top-left</hotspot>
                        <wrapping>Word</wrapping>
                        <line-height>0</line-height>
                    </properties>
                    <blend-mode>0</blend-mode>
                    <effect-fallback>0</effect-fallback>
                    <world>
                        <x>311</x>
                        <y>197</y>
                        <z>0</z>
                        <width>200</width>
                        <height>34</height>
                        <depth>0</depth>
                        <hotspotX>0</hotspotX>
                        <hotspotY>0</hotspotY>
                        <angle>0</angle>
                        <opacity>1</opacity>
                    </world>
                </instance>
            </instances>
            <effects />
        </layer>
    </layers>
    <nonworld-instances />
    <effects />
</c2layout>
